stylist/__init__.py
stylist/__version__.py
stylist/admin.py
stylist/apps.py
stylist/context_processors.py
stylist/forms.py
stylist/models.py
stylist/settings.py
stylist/tests.py
stylist/urls.py
stylist/utils.py
stylist/views.py
stylist/api/__init__.py
stylist/api/serializers.py
stylist/api/urls.py
stylist/api/views.py
stylist/management/__init__.py
stylist/management/commands/__init__.py
stylist/management/commands/build_scss.py
stylist/management/commands/sync_google_fonts.py
stylist/migrations/0001_initial.py
stylist/migrations/0002_auto_20210114_1901.py
stylist/migrations/0003_font.py
stylist/migrations/__init__.py
stylist/templates/stylist/active_form.html
stylist/templates/stylist/base.html
stylist/templates/stylist/index.html
stylist/templates/stylist/style_delete.html
stylist/templates/stylist/style_form.html
django_stylist-0.2.4.dist-info/LICENSE.mit.txt
django_stylist-0.2.4.dist-info/METADATA
django_stylist-0.2.4.dist-info/WHEEL
django_stylist-0.2.4.dist-info/top_level.txt
django_stylist-0.2.4.dist-info/RECORD
